apksigcopier/__init__.py
apksigcopier/py.typed
apksigcopier-1.1.1.dist-info/LICENSE.GPLv3
apksigcopier-1.1.1.dist-info/METADATA
apksigcopier-1.1.1.dist-info/WHEEL
apksigcopier-1.1.1.dist-info/entry_points.txt
apksigcopier-1.1.1.dist-info/top_level.txt
apksigcopier-1.1.1.dist-info/RECORD
